projdir/__init__.py
projdir/core.py
projdir-0.1.1.dist-info/LICENSE
projdir-0.1.1.dist-info/METADATA
projdir-0.1.1.dist-info/WHEEL
projdir-0.1.1.dist-info/top_level.txt
projdir-0.1.1.dist-info/RECORD
