Metadata-Version: 2.1
Name: projdir
Version: 0.1.1
Summary: Locate a project directory or a config file.
Home-page: https://github.com/rasmuse/python-projdir
Author: Rasmus Einarsson
Author-email: mr@rasmuseinarsson.se
Maintainer: Rasmus Einarsson
Maintainer-email: python-projdir@rasmuseinarsson.se
License: MIT License
Project-URL: Source Code, https://github.com/rasmuse/python-projdir
Project-URL: Issue Tracker, https://github.com/rasmuse/python-projdir/issues
Platform: UNKNOWN
Classifier: Development Status :: 4 - Beta
Classifier: Intended Audience :: Developers
Classifier: License :: OSI Approved :: MIT License
Classifier: Programming Language :: Python
Classifier: Programming Language :: Python :: 3
Classifier: Programming Language :: Python :: 3.6
Classifier: Programming Language :: Python :: 3.7
Classifier: Programming Language :: Python :: 3.8
Classifier: Programming Language :: Python :: 3.9
Classifier: Programming Language :: Python :: 3.10
Classifier: Programming Language :: Python :: 3.11
Classifier: Topic :: Software Development
Requires-Python: >=3.6
License-File: LICENSE
